RZlogger/__init__.py
RZlogger/logger.py
RZlogger-1.0.4.dist-info/METADATA
RZlogger-1.0.4.dist-info/WHEEL
RZlogger-1.0.4.dist-info/top_level.txt
RZlogger-1.0.4.dist-info/RECORD
