Metadata-Version: 2.1
Name: RZlogger
Version: 1.0.4
Summary: RZlogger
Home-page: 
Author: rahim
Author-email: zenith.rahim@gmail.com
License: MIT
Keywords: RZlogger rest realtime pub/sub and rpc service
Classifier: License :: OSI Approved :: MIT License
Classifier: Development Status :: 4 - Beta
Classifier: Intended Audience :: Developers
Classifier: Programming Language :: Python :: 3.6
Classifier: Programming Language :: Python :: 3.7
Classifier: Programming Language :: Python :: 3.8
Classifier: Programming Language :: Python :: 3.9
Classifier: Programming Language :: Python :: 3.10
